setup.py
mghari_distributions/Binomialdistribution.py
mghari_distributions/Gaussiandistribution.py
mghari_distributions/Generaldistribution.py
mghari_distributions/__init__.py
mghari_distributions.egg-info/PKG-INFO
mghari_distributions.egg-info/SOURCES.txt
mghari_distributions.egg-info/dependency_links.txt
mghari_distributions.egg-info/not-zip-safe
mghari_distributions.egg-info/top_level.txt