Metadata-Version: 1.0
Name: mghari-distributions
Version: 0.1
Summary: Gaussian and Binomial distributions
Home-page: UNKNOWN
Author: Mohammed Mghari
Author-email: med.mghari@gmail.com
License: UNKNOWN
Platform: UNKNOWN
